fastbots/__init__.py
fastbots/bot.py
fastbots/chrome_bot.py
fastbots/config.py
fastbots/exceptions.py
fastbots/firefox_bot.py
fastbots/llm_extractor.py
fastbots/logger.py
fastbots/page.py
fastbots/payload.py
fastbots/task.py
fastbots-0.2.7.dist-info/LICENSE
fastbots-0.2.7.dist-info/METADATA
fastbots-0.2.7.dist-info/WHEEL
fastbots-0.2.7.dist-info/RECORD
