Metadata-Version: 2.1
Name: fastbots
Version: 0.2.7
Summary: A simple library designed for rapid bot and scraper development using Selenium and the POM (Page Object Model) design.
License: LICENSE
Author: Uberti Davide
Author-email: 24529587+ubertidavide@users.noreply.github.com
Requires-Python: >=3.11,<4.0
Classifier: License :: Other/Proprietary License
Classifier: Programming Language :: Python :: 3
Classifier: Programming Language :: Python :: 3.11
Classifier: Programming Language :: Python :: 3.12
Requires-Dist: capsolver (>=1.0.7,<2.0.0)
Requires-Dist: langchain (>=0.1.16,<0.2.0)
Requires-Dist: langchain-openai (>=0.1.3,<0.2.0)
Requires-Dist: python-decouple (>=3.8,<4.0)
Requires-Dist: selenium (>=4.15.2,<5.0.0)
Requires-Dist: selenium-wire (>=5.1.0,<6.0.0)
Requires-Dist: tenacity (>=8.2.3,<9.0.0)
